[
    {
        "option_name": "name",
        "type": "string",
        "description": [
            "Name for the LSN ip6 profile. Must begin with an ASCII alphanumeric or underscore (_) character, and must contain only ASCII alphanumeric, underscore, hash (#), period (.), space, colon (:), at (@), equals (=), and hyphen (-) characters. Cannot be changed after the LSN ip6 profile is created. The following requirement applies only to the Citrix ADC CLI: If the name includes one or more spaces, enclose the name in double or single quotation marks (for example, \"lsn ip6 profile1\" or 'lsn ip6 profile1')."
        ],
        "is_get_id": true,
        "is_delete_id": true,
        "is_updateable": false,
        "is_required": true,
        "x-unique-attr": true
    },
    {
        "option_name": "natprefix",
        "type": "string",
        "description": [
            "IPv6 address(es) of the LSN subscriber(s) or subscriber network(s) on whose traffic you want the Citrix ADC to perform Large Scale NAT."
        ],
        "is_get_id": false,
        "is_delete_id": false,
        "is_updateable": false,
        "is_required": false
    },
    {
        "option_name": "network6",
        "type": "string",
        "description": [
            "IPv6 address of the Citrix ADC AFTR device"
        ],
        "is_get_id": false,
        "is_delete_id": false,
        "is_updateable": false,
        "is_required": false
    },
    {
        "option_name": "type",
        "type": "string",
        "description": [
            "IPv6 translation type for which to set the LSN IP6 profile parameters."
        ],
        "is_get_id": false,
        "is_delete_id": false,
        "is_updateable": false,
        "is_required": true
    }
]