[
    {
        "option_name": "announcemulticount",
        "type": "integer",
        "description": [
            "Integer value that identify the number announce message to be send."
        ],
        "is_get_id": false,
        "is_delete_id": false,
        "is_updateable": true,
        "is_required": false,
        "default": 10
    },
    {
        "option_name": "mapping",
        "type": "string",
        "description": [
            "This argument is for enabling/disabling the MAP opcode  of current PCP Profile"
        ],
        "is_get_id": false,
        "is_delete_id": false,
        "is_updateable": true,
        "is_required": false,
        "default": "ENABLED"
    },
    {
        "option_name": "maxmaplife",
        "type": "integer",
        "description": [
            "Integer value that identify the maximum mapping lifetime (in seconds) for a pcp profile. default(86400s = 24Hours)."
        ],
        "is_get_id": false,
        "is_delete_id": false,
        "is_updateable": true,
        "is_required": false
    },
    {
        "option_name": "minmaplife",
        "type": "integer",
        "description": [
            "Integer value that identify the minimum mapping lifetime (in seconds) for a pcp profile. default(120s)"
        ],
        "is_get_id": false,
        "is_delete_id": false,
        "is_updateable": true,
        "is_required": false
    },
    {
        "option_name": "name",
        "type": "string",
        "description": [
            "Name for the PCP Profile. Must begin with an ASCII alphanumeric or underscore (_) character, and must contain only ASCII alphanumeric, underscore CLI Users: If the name includes one or more spaces, enclose the name in double or single quotation marks (for example, \"my pcpProfile\" or my pcpProfile)."
        ],
        "is_get_id": true,
        "is_delete_id": true,
        "is_updateable": false,
        "is_required": true,
        "x-unique-attr": true
    },
    {
        "option_name": "peer",
        "type": "string",
        "description": [
            "This argument is for enabling/disabling the PEER opcode of current PCP Profile"
        ],
        "is_get_id": false,
        "is_delete_id": false,
        "is_updateable": true,
        "is_required": false,
        "default": "ENABLED"
    },
    {
        "option_name": "thirdparty",
        "type": "string",
        "description": [
            "This argument is for enabling/disabling the THIRD PARTY opcode of current PCP Profile"
        ],
        "is_get_id": false,
        "is_delete_id": false,
        "is_updateable": true,
        "is_required": false,
        "default": "DISABLED"
    }
]